setup.py
bin/debmeo
debmeo/__init__.py
debmeo/discover.py
debmeo/io.py
debmeo.egg-info/PKG-INFO
debmeo.egg-info/SOURCES.txt
debmeo.egg-info/dependency_links.txt
debmeo.egg-info/requires.txt
debmeo.egg-info/top_level.txt