Metadata-Version: 1.0
Name: debmeo
Version: 2.1.1
Summary: Get oEmbed info asynchronously
Home-page: http://github.com/bmuller/debmeo
Author: Brian Muller
Author-email: bamuller@gmail.com
License: MIT
Platform: UNKNOWN
